eputils/__init__.py
eputils/thread/__init__.py
eputils/thread/abstract.py
eputils/thread/consumer.py
eputils/thread/publisher.py
eputils/thread/settings.py
eputils-2022.11.25.1611.dist-info/LICENSE
eputils-2022.11.25.1611.dist-info/METADATA
eputils-2022.11.25.1611.dist-info/WHEEL
eputils-2022.11.25.1611.dist-info/top_level.txt
eputils-2022.11.25.1611.dist-info/RECORD
