Metadata-Version: 2.1
Name: eputils
Version: 2022.11.25.1611
Requires-Python: >=3.10
License-File: LICENSE
Requires-Dist: pika
